main.py
newpy/__init__.py
newpy/cli_builder.py
newpy/errors.py
newpy/license.py
newpy/repo.py
newpy/setup_manager.py
newpy/templ_gitignore.py
newpy/templ_setup.py
startnew-1.3.6.dist-info/AUTHORS.md
startnew-1.3.6.dist-info/LICENSE
startnew-1.3.6.dist-info/METADATA
startnew-1.3.6.dist-info/WHEEL
startnew-1.3.6.dist-info/entry_points.txt
startnew-1.3.6.dist-info/top_level.txt
startnew-1.3.6.dist-info/RECORD
