Metadata-Version: 2.1
Name: startnew
Version: 1.3.6
Summary: Start new python project with this light cli tool
Home-page: https://github.com/stefangal/newpy
Author: Stefan Gal
Author-email: "stefan.mail.sk@gmail.com
License: mit
Keywords: newpy,skeleton,structure,new project,template
Platform: UNKNOWN
Classifier: Programming Language :: Python :: 3
Classifier: License :: OSI Approved :: MIT License
Classifier: Operating System :: MacOS :: MacOS X
Requires-Dist: attrs (==20.3.0)
Requires-Dist: bleach (==3.2.1)
Requires-Dist: certifi (==2020.11.8)
Requires-Dist: chardet (==3.0.4)
Requires-Dist: Click (==7.0)
Requires-Dist: colorama (==0.4.3)
Requires-Dist: Deprecated (==1.2.10)
Requires-Dist: docutils (==0.16)
Requires-Dist: idna (==2.10)
Requires-Dist: iniconfig (==1.1.1)
Requires-Dist: keyring (==21.5.0)
Requires-Dist: lice (==0.6)
Requires-Dist: mock (==4.0.2)
Requires-Dist: packaging (==20.4)
Requires-Dist: pkginfo (==1.6.1)
Requires-Dist: pluggy (==0.13.1)
Requires-Dist: py (==1.9.0)
Requires-Dist: PyGithub (==1.53)
Requires-Dist: Pygments (==2.7.2)
Requires-Dist: PyJWT (==1.7.1)
Requires-Dist: pyparsing (==2.4.7)
Requires-Dist: pytest (==6.1.1)
Requires-Dist: readme-renderer (==28.0)
Requires-Dist: requests (==2.24.0)
Requires-Dist: requests-toolbelt (==0.9.1)
Requires-Dist: rfc3986 (==1.4.0)
Requires-Dist: six (==1.15.0)
Requires-Dist: toml (==0.10.2)
Requires-Dist: tqdm (==4.51.0)
Requires-Dist: urllib3 (==1.25.11)
Requires-Dist: webencodings (==0.5.1)
Requires-Dist: wrapt (==1.12.1)
